nendo_plugin_loopify/__init__.py
nendo_plugin_loopify/beatnet.py
nendo_plugin_loopify/models/model.pt
nendo_plugin_loopify/plugin.py
nendo_plugin_loopify/utils.py
nendo_plugin_loopify-0.1.7.dist-info/LICENSE
nendo_plugin_loopify-0.1.7.dist-info/METADATA
nendo_plugin_loopify-0.1.7.dist-info/WHEEL
nendo_plugin_loopify-0.1.7.dist-info/RECORD
