Metadata-Version: 2.1
Name: nendo-plugin-loopify
Version: 0.1.7
Summary: Nendo plugin for automatic audio loop extraction.
Home-page: https://okio.ai
License: MIT
Keywords: Nendo,Plugin,Loopification,Music loop generation,AI,Machine Learning,Audio,Generative,Music,Audio Production,Audio Generation,Audio Analysis
Author: Aaron Abebe
Author-email: aaron@okio.ai
Requires-Python: >=3.8,<3.11
Classifier: Development Status :: 5 - Production/Stable
Classifier: Intended Audience :: Developers
Classifier: License :: OSI Approved :: MIT License
Classifier: Operating System :: OS Independent
Classifier: Programming Language :: Python :: 3
Classifier: Programming Language :: Python :: 3.8
Classifier: Programming Language :: Python :: 3.9
Classifier: Programming Language :: Python :: 3.10
Classifier: Topic :: Multimedia :: Sound/Audio
Requires-Dist: nendo (>=0.2.0,<0.3.0)
Requires-Dist: pydantic (>=2.0.0,<2.5.0)
Requires-Dist: pydantic-settings (>=2.1.0,<3.0.0)
Project-URL: Repository, https://github.com/okio-ai/nendo_plugin_loopify
